rapidfire/__init__.py
rapidfire/ansi.py
rapidfire/clipboard.py
rapidfire/config.py
rapidfire/core.py
rapidfire/exceptions.py
rapidfire/keys.py
rapidfire/pager.py
rapidfire/parser.py
rapidfire/run.py
rapidfire/terminalsize.py
rapidfire-1.0.0.dist-info/DESCRIPTION.rst
rapidfire-1.0.0.dist-info/entry_points.txt
rapidfire-1.0.0.dist-info/METADATA
rapidfire-1.0.0.dist-info/metadata.json
rapidfire-1.0.0.dist-info/RECORD
rapidfire-1.0.0.dist-info/top_level.txt
rapidfire-1.0.0.dist-info/WHEEL
