Metadata-Version: 2.0
Name: rapidfire
Version: 1.0.0
Summary: rapidfire calls and displays the defined Python function from command line
Home-page: https://github.com/wanshot/RapidFire
Author: wanshot
Author-email: nishikawa0228@sj9.so-net.ne.jp
License: MIT
Keywords: cli,command line interface,shell
Platform: UNKNOWN
Classifier: Programming Language :: Python
Classifier: Development Status :: 5 - Production/Stable
Classifier: Topic :: Software Development
Classifier: Programming Language :: Python :: 3
Classifier: Topic :: Terminals
Requires-Dist: wcwidth
